pylematch/__init__.py
pylematch/pylematch.py
pylematch-0.0.1.241223.dist-info/LICENSE.txt
pylematch-0.0.1.241223.dist-info/WHEEL
pylematch-0.0.1.241223.dist-info/METADATA
pylematch-0.0.1.241223.dist-info/RECORD
