Metadata-Version: 2.3
Name: pylematch
Version: 0.0.1.241223
Summary: Pylematch: A module for matching file system paths against patterns.
Home-page: https://github.com/codyverse/pylematch
License: MIT
Keywords: file matching, file filter, filter, patterns, ignore, gitignore, dockerignore
Author: Andrii Burkatskyi aka andr11b
Author-email: 4ndr116@gmail.com
Requires-Python: >=3.8
Requires-Dist: pytest>=6.0 ; extra == "dev"
Provides-Extra: dev
